{"titles": ["82\ub144\uc0dd \uae40\uc9c0\uc601", "\uac10\uc2dc\uc640 \ucc98\ubc8c", "\ud53c\ub85c\uc0ac\ud68c", "\uc790\uc720\ub860", "\ub9cc\ub4e4\uc5b4\uc9c4 \uc2e0"], "indices": [554769, 188467, 222213, 425200, 223135], "sims": [0.456579541953068, 0.39194959177119504, 0.38999093461547785, 0.38650110577767566, 0.37938753652434987], "unions": [{"sets": ["\ub9cc\ub4e4\uc5b4\uc9c4 \uc2e0"], "size": 629}, {"sets": ["\uc790\uc720\ub860"], "size": 440}, {"sets": ["\uc790\uc720\ub860", "\ub9cc\ub4e4\uc5b4\uc9c4 \uc2e0"], "size": 128}, {"sets": ["\ud53c\ub85c\uc0ac\ud68c"], "size": 571}, {"sets": ["\ud53c\ub85c\uc0ac\ud68c", "\ub9cc\ub4e4\uc5b4\uc9c4 \uc2e0"], "size": 145}, {"sets": ["\ud53c\ub85c\uc0ac\ud68c", "\uc790\uc720\ub860"], "size": 107}, {"sets": ["\ud53c\ub85c\uc0ac\ud68c", "\uc790\uc720\ub860", "\ub9cc\ub4e4\uc5b4\uc9c4 \uc2e0"], "size": 59}, {"sets": ["\uac10\uc2dc\uc640 \ucc98\ubc8c"], "size": 256}, {"sets": ["\uac10\uc2dc\uc640 \ucc98\ubc8c", "\ub9cc\ub4e4\uc5b4\uc9c4 \uc2e0"], "size": 103}, {"sets": ["\uac10\uc2dc\uc640 \ucc98\ubc8c", "\uc790\uc720\ub860"], "size": 71}, {"sets": ["\uac10\uc2dc\uc640 \ucc98\ubc8c", "\uc790\uc720\ub860", "\ub9cc\ub4e4\uc5b4\uc9c4 \uc2e0"], "size": 50}, {"sets": ["\uac10\uc2dc\uc640 \ucc98\ubc8c", "\ud53c\ub85c\uc0ac\ud68c"], "size": 93}, {"sets": ["\uac10\uc2dc\uc640 \ucc98\ubc8c", "\ud53c\ub85c\uc0ac\ud68c", "\ub9cc\ub4e4\uc5b4\uc9c4 \uc2e0"], "size": 57}, {"sets": ["\uac10\uc2dc\uc640 \ucc98\ubc8c", "\ud53c\ub85c\uc0ac\ud68c", "\uc790\uc720\ub860"], "size": 41}, {"sets": ["\uac10\uc2dc\uc640 \ucc98\ubc8c", "\ud53c\ub85c\uc0ac\ud68c", "\uc790\uc720\ub860", "\ub9cc\ub4e4\uc5b4\uc9c4 \uc2e0"], "size": 35}, {"sets": ["82\ub144\uc0dd \uae40\uc9c0\uc601"], "size": 2284}, {"sets": ["82\ub144\uc0dd \uae40\uc9c0\uc601", "\ub9cc\ub4e4\uc5b4\uc9c4 \uc2e0"], "size": 171}, {"sets": ["82\ub144\uc0dd \uae40\uc9c0\uc601", "\uc790\uc720\ub860"], "size": 113}, {"sets": ["82\ub144\uc0dd \uae40\uc9c0\uc601", "\uc790\uc720\ub860", "\ub9cc\ub4e4\uc5b4\uc9c4 \uc2e0"], "size": 53}, {"sets": ["82\ub144\uc0dd \uae40\uc9c0\uc601", "\ud53c\ub85c\uc0ac\ud68c"], "size": 190}, {"sets": ["82\ub144\uc0dd \uae40\uc9c0\uc601", "\ud53c\ub85c\uc0ac\ud68c", "\ub9cc\ub4e4\uc5b4\uc9c4 \uc2e0"], "size": 68}, {"sets": ["82\ub144\uc0dd \uae40\uc9c0\uc601", "\ud53c\ub85c\uc0ac\ud68c", "\uc790\uc720\ub860"], "size": 52}, {"sets": ["82\ub144\uc0dd \uae40\uc9c0\uc601", "\ud53c\ub85c\uc0ac\ud68c", "\uc790\uc720\ub860", "\ub9cc\ub4e4\uc5b4\uc9c4 \uc2e0"], "size": 35}, {"sets": ["82\ub144\uc0dd \uae40\uc9c0\uc601", "\uac10\uc2dc\uc640 \ucc98\ubc8c"], "size": 86}, {"sets": ["82\ub144\uc0dd \uae40\uc9c0\uc601", "\uac10\uc2dc\uc640 \ucc98\ubc8c", "\ub9cc\ub4e4\uc5b4\uc9c4 \uc2e0"], "size": 51}, {"sets": ["82\ub144\uc0dd \uae40\uc9c0\uc601", "\uac10\uc2dc\uc640 \ucc98\ubc8c", "\uc790\uc720\ub860"], "size": 38}, {"sets": ["82\ub144\uc0dd \uae40\uc9c0\uc601", "\uac10\uc2dc\uc640 \ucc98\ubc8c", "\uc790\uc720\ub860", "\ub9cc\ub4e4\uc5b4\uc9c4 \uc2e0"], "size": 30}, {"sets": ["82\ub144\uc0dd \uae40\uc9c0\uc601", "\uac10\uc2dc\uc640 \ucc98\ubc8c", "\ud53c\ub85c\uc0ac\ud68c"], "size": 49}, {"sets": ["82\ub144\uc0dd \uae40\uc9c0\uc601", "\uac10\uc2dc\uc640 \ucc98\ubc8c", "\ud53c\ub85c\uc0ac\ud68c", "\ub9cc\ub4e4\uc5b4\uc9c4 \uc2e0"], "size": 33}, {"sets": ["82\ub144\uc0dd \uae40\uc9c0\uc601", "\uac10\uc2dc\uc640 \ucc98\ubc8c", "\ud53c\ub85c\uc0ac\ud68c", "\uc790\uc720\ub860"], "size": 27}, {"sets": ["82\ub144\uc0dd \uae40\uc9c0\uc601", "\uac10\uc2dc\uc640 \ucc98\ubc8c", "\ud53c\ub85c\uc0ac\ud68c", "\uc790\uc720\ub860", "\ub9cc\ub4e4\uc5b4\uc9c4 \uc2e0"], "size": 23}]}