{"titles": ["\uc624\ubca0\ub77c\ub294 \ub0a8\uc790", "\ub77c\ud50c\ub77c\uc2a4\uc758 \ub9c8\ub140", "1Q84 2", "1Q84 1", "\uc81c3\uc778\ub958 1"], "indices": [554769, 188467, 222213, 425200, 223135], "sims": [0.2488333314141785, 0.23719179418353428, 0.2301141066948878, 0.22061349016651233, 0.21139502363116305], "unions": [{"sets": ["\uc81c3\uc778\ub958 1"], "size": 369}, {"sets": ["1Q84 1"], "size": 926}, {"sets": ["1Q84 1", "\uc81c3\uc778\ub958 1"], "size": 116}, {"sets": ["1Q84 2"], "size": 696}, {"sets": ["1Q84 2", "\uc81c3\uc778\ub958 1"], "size": 91}, {"sets": ["1Q84 2", "1Q84 1"], "size": 644}, {"sets": ["1Q84 2", "1Q84 1", "\uc81c3\uc778\ub958 1"], "size": 87}, {"sets": ["\ub77c\ud50c\ub77c\uc2a4\uc758 \ub9c8\ub140"], "size": 524}, {"sets": ["\ub77c\ud50c\ub77c\uc2a4\uc758 \ub9c8\ub140", "\uc81c3\uc778\ub958 1"], "size": 69}, {"sets": ["\ub77c\ud50c\ub77c\uc2a4\uc758 \ub9c8\ub140", "1Q84 1"], "size": 127}, {"sets": ["\ub77c\ud50c\ub77c\uc2a4\uc758 \ub9c8\ub140", "1Q84 1", "\uc81c3\uc778\ub958 1"], "size": 38}, {"sets": ["\ub77c\ud50c\ub77c\uc2a4\uc758 \ub9c8\ub140", "1Q84 2"], "size": 98}, {"sets": ["\ub77c\ud50c\ub77c\uc2a4\uc758 \ub9c8\ub140", "1Q84 2", "\uc81c3\uc778\ub958 1"], "size": 30}, {"sets": ["\ub77c\ud50c\ub77c\uc2a4\uc758 \ub9c8\ub140", "1Q84 2", "1Q84 1"], "size": 94}, {"sets": ["\ub77c\ud50c\ub77c\uc2a4\uc758 \ub9c8\ub140", "1Q84 2", "1Q84 1", "\uc81c3\uc778\ub958 1"], "size": 29}, {"sets": ["\uc624\ubca0\ub77c\ub294 \ub0a8\uc790"], "size": 813}, {"sets": ["\uc624\ubca0\ub77c\ub294 \ub0a8\uc790", "\uc81c3\uc778\ub958 1"], "size": 77}, {"sets": ["\uc624\ubca0\ub77c\ub294 \ub0a8\uc790", "1Q84 1"], "size": 171}, {"sets": ["\uc624\ubca0\ub77c\ub294 \ub0a8\uc790", "1Q84 1", "\uc81c3\uc778\ub958 1"], "size": 34}, {"sets": ["\uc624\ubca0\ub77c\ub294 \ub0a8\uc790", "1Q84 2"], "size": 125}, {"sets": ["\uc624\ubca0\ub77c\ub294 \ub0a8\uc790", "1Q84 2", "\uc81c3\uc778\ub958 1"], "size": 27}, {"sets": ["\uc624\ubca0\ub77c\ub294 \ub0a8\uc790", "1Q84 2", "1Q84 1"], "size": 115}, {"sets": ["\uc624\ubca0\ub77c\ub294 \ub0a8\uc790", "1Q84 2", "1Q84 1", "\uc81c3\uc778\ub958 1"], "size": 26}, {"sets": ["\uc624\ubca0\ub77c\ub294 \ub0a8\uc790", "\ub77c\ud50c\ub77c\uc2a4\uc758 \ub9c8\ub140"], "size": 138}, {"sets": ["\uc624\ubca0\ub77c\ub294 \ub0a8\uc790", "\ub77c\ud50c\ub77c\uc2a4\uc758 \ub9c8\ub140", "\uc81c3\uc778\ub958 1"], "size": 31}, {"sets": ["\uc624\ubca0\ub77c\ub294 \ub0a8\uc790", "\ub77c\ud50c\ub77c\uc2a4\uc758 \ub9c8\ub140", "1Q84 1"], "size": 60}, {"sets": ["\uc624\ubca0\ub77c\ub294 \ub0a8\uc790", "\ub77c\ud50c\ub77c\uc2a4\uc758 \ub9c8\ub140", "1Q84 1", "\uc81c3\uc778\ub958 1"], "size": 20}, {"sets": ["\uc624\ubca0\ub77c\ub294 \ub0a8\uc790", "\ub77c\ud50c\ub77c\uc2a4\uc758 \ub9c8\ub140", "1Q84 2"], "size": 46}, {"sets": ["\uc624\ubca0\ub77c\ub294 \ub0a8\uc790", "\ub77c\ud50c\ub77c\uc2a4\uc758 \ub9c8\ub140", "1Q84 2", "\uc81c3\uc778\ub958 1"], "size": 17}, {"sets": ["\uc624\ubca0\ub77c\ub294 \ub0a8\uc790", "\ub77c\ud50c\ub77c\uc2a4\uc758 \ub9c8\ub140", "1Q84 2", "1Q84 1"], "size": 45}, {"sets": ["\uc624\ubca0\ub77c\ub294 \ub0a8\uc790", "\ub77c\ud50c\ub77c\uc2a4\uc758 \ub9c8\ub140", "1Q84 2", "1Q84 1", "\uc81c3\uc778\ub958 1"], "size": 17}]}