{"titles": ["\uc704\ub300\ud55c \uac1c\uce20\ube44", "\uc624\ubca0\ub77c\ub294 \ub0a8\uc790", "7\ub144\uc758 \ubc24", "\ub300\uc131\ub2f9", "\ud551\uac70\uc2a4\ubbf8\uc2a4"], "indices": [554769, 188467, 222213, 425200, 223135], "sims": [0.7164115207792252, 0.6923214964237498, 0.675505684952587, 0.6684062403058583, 0.6400554635456838], "unions": [{"sets": ["\ud551\uac70\uc2a4\ubbf8\uc2a4"], "size": 140}, {"sets": ["\ub300\uc131\ub2f9"], "size": 231}, {"sets": ["\ub300\uc131\ub2f9", "\ud551\uac70\uc2a4\ubbf8\uc2a4"], "size": 25}, {"sets": ["7\ub144\uc758 \ubc24"], "size": 1309}, {"sets": ["7\ub144\uc758 \ubc24", "\ud551\uac70\uc2a4\ubbf8\uc2a4"], "size": 64}, {"sets": ["7\ub144\uc758 \ubc24", "\ub300\uc131\ub2f9"], "size": 92}, {"sets": ["7\ub144\uc758 \ubc24", "\ub300\uc131\ub2f9", "\ud551\uac70\uc2a4\ubbf8\uc2a4"], "size": 12}, {"sets": ["\uc624\ubca0\ub77c\ub294 \ub0a8\uc790"], "size": 813}, {"sets": ["\uc624\ubca0\ub77c\ub294 \ub0a8\uc790", "\ud551\uac70\uc2a4\ubbf8\uc2a4"], "size": 41}, {"sets": ["\uc624\ubca0\ub77c\ub294 \ub0a8\uc790", "\ub300\uc131\ub2f9"], "size": 54}, {"sets": ["\uc624\ubca0\ub77c\ub294 \ub0a8\uc790", "\ub300\uc131\ub2f9", "\ud551\uac70\uc2a4\ubbf8\uc2a4"], "size": 9}, {"sets": ["\uc624\ubca0\ub77c\ub294 \ub0a8\uc790", "7\ub144\uc758 \ubc24"], "size": 270}, {"sets": ["\uc624\ubca0\ub77c\ub294 \ub0a8\uc790", "7\ub144\uc758 \ubc24", "\ud551\uac70\uc2a4\ubbf8\uc2a4"], "size": 28}, {"sets": ["\uc624\ubca0\ub77c\ub294 \ub0a8\uc790", "7\ub144\uc758 \ubc24", "\ub300\uc131\ub2f9"], "size": 37}, {"sets": ["\uc624\ubca0\ub77c\ub294 \ub0a8\uc790", "7\ub144\uc758 \ubc24", "\ub300\uc131\ub2f9", "\ud551\uac70\uc2a4\ubbf8\uc2a4"], "size": 6}, {"sets": ["\uc704\ub300\ud55c \uac1c\uce20\ube44"], "size": 283}, {"sets": ["\uc704\ub300\ud55c \uac1c\uce20\ube44", "\ud551\uac70\uc2a4\ubbf8\uc2a4"], "size": 15}, {"sets": ["\uc704\ub300\ud55c \uac1c\uce20\ube44", "\ub300\uc131\ub2f9"], "size": 46}, {"sets": ["\uc704\ub300\ud55c \uac1c\uce20\ube44", "\ub300\uc131\ub2f9", "\ud551\uac70\uc2a4\ubbf8\uc2a4"], "size": 11}, {"sets": ["\uc704\ub300\ud55c \uac1c\uce20\ube44", "7\ub144\uc758 \ubc24"], "size": 98}, {"sets": ["\uc704\ub300\ud55c \uac1c\uce20\ube44", "7\ub144\uc758 \ubc24", "\ud551\uac70\uc2a4\ubbf8\uc2a4"], "size": 8}, {"sets": ["\uc704\ub300\ud55c \uac1c\uce20\ube44", "7\ub144\uc758 \ubc24", "\ub300\uc131\ub2f9"], "size": 26}, {"sets": ["\uc704\ub300\ud55c \uac1c\uce20\ube44", "7\ub144\uc758 \ubc24", "\ub300\uc131\ub2f9", "\ud551\uac70\uc2a4\ubbf8\uc2a4"], "size": 7}, {"sets": ["\uc704\ub300\ud55c \uac1c\uce20\ube44", "\uc624\ubca0\ub77c\ub294 \ub0a8\uc790"], "size": 47}, {"sets": ["\uc704\ub300\ud55c \uac1c\uce20\ube44", "\uc624\ubca0\ub77c\ub294 \ub0a8\uc790", "\ud551\uac70\uc2a4\ubbf8\uc2a4"], "size": 4}, {"sets": ["\uc704\ub300\ud55c \uac1c\uce20\ube44", "\uc624\ubca0\ub77c\ub294 \ub0a8\uc790", "\ub300\uc131\ub2f9"], "size": 10}, {"sets": ["\uc704\ub300\ud55c \uac1c\uce20\ube44", "\uc624\ubca0\ub77c\ub294 \ub0a8\uc790", "\ub300\uc131\ub2f9", "\ud551\uac70\uc2a4\ubbf8\uc2a4"], "size": 3}, {"sets": ["\uc704\ub300\ud55c \uac1c\uce20\ube44", "\uc624\ubca0\ub77c\ub294 \ub0a8\uc790", "7\ub144\uc758 \ubc24"], "size": 34}, {"sets": ["\uc704\ub300\ud55c \uac1c\uce20\ube44", "\uc624\ubca0\ub77c\ub294 \ub0a8\uc790", "7\ub144\uc758 \ubc24", "\ud551\uac70\uc2a4\ubbf8\uc2a4"], "size": 4}, {"sets": ["\uc704\ub300\ud55c \uac1c\uce20\ube44", "\uc624\ubca0\ub77c\ub294 \ub0a8\uc790", "7\ub144\uc758 \ubc24", "\ub300\uc131\ub2f9"], "size": 10}, {"sets": ["\uc704\ub300\ud55c \uac1c\uce20\ube44", "\uc624\ubca0\ub77c\ub294 \ub0a8\uc790", "7\ub144\uc758 \ubc24", "\ub300\uc131\ub2f9", "\ud551\uac70\uc2a4\ubbf8\uc2a4"], "size": 3}]}