{"titles": ["\uc81c\ub85c \ud22c \uc6d0", "\ud3ec\uc9c0\uc154\ub2dd POSITIONING", "\uacbd\uc601\uc758 \ubaa8\ud5d8", "\uc624\ub9ac\uc9c0\ub110\uc2a4", "\uc2e0\ud638\uc640 \uc18c\uc74c"], "indices": [554769, 188467, 222213, 425200, 223135], "sims": [0.49087119897529835, 0.46874849608927155, 0.4557567552060551, 0.4522536756677392, 0.445635087073994], "unions": [{"sets": ["\uc2e0\ud638\uc640 \uc18c\uc74c"], "size": 240}, {"sets": ["\uc624\ub9ac\uc9c0\ub110\uc2a4"], "size": 536}, {"sets": ["\uc624\ub9ac\uc9c0\ub110\uc2a4", "\uc2e0\ud638\uc640 \uc18c\uc74c"], "size": 80}, {"sets": ["\uacbd\uc601\uc758 \ubaa8\ud5d8"], "size": 270}, {"sets": ["\uacbd\uc601\uc758 \ubaa8\ud5d8", "\uc2e0\ud638\uc640 \uc18c\uc74c"], "size": 53}, {"sets": ["\uacbd\uc601\uc758 \ubaa8\ud5d8", "\uc624\ub9ac\uc9c0\ub110\uc2a4"], "size": 82}, {"sets": ["\uacbd\uc601\uc758 \ubaa8\ud5d8", "\uc624\ub9ac\uc9c0\ub110\uc2a4", "\uc2e0\ud638\uc640 \uc18c\uc74c"], "size": 30}, {"sets": ["\ud3ec\uc9c0\uc154\ub2dd POSITIONING"], "size": 227}, {"sets": ["\ud3ec\uc9c0\uc154\ub2dd POSITIONING", "\uc2e0\ud638\uc640 \uc18c\uc74c"], "size": 48}, {"sets": ["\ud3ec\uc9c0\uc154\ub2dd POSITIONING", "\uc624\ub9ac\uc9c0\ub110\uc2a4"], "size": 60}, {"sets": ["\ud3ec\uc9c0\uc154\ub2dd POSITIONING", "\uc624\ub9ac\uc9c0\ub110\uc2a4", "\uc2e0\ud638\uc640 \uc18c\uc74c"], "size": 21}, {"sets": ["\ud3ec\uc9c0\uc154\ub2dd POSITIONING", "\uacbd\uc601\uc758 \ubaa8\ud5d8"], "size": 42}, {"sets": ["\ud3ec\uc9c0\uc154\ub2dd POSITIONING", "\uacbd\uc601\uc758 \ubaa8\ud5d8", "\uc2e0\ud638\uc640 \uc18c\uc74c"], "size": 18}, {"sets": ["\ud3ec\uc9c0\uc154\ub2dd POSITIONING", "\uacbd\uc601\uc758 \ubaa8\ud5d8", "\uc624\ub9ac\uc9c0\ub110\uc2a4"], "size": 22}, {"sets": ["\ud3ec\uc9c0\uc154\ub2dd POSITIONING", "\uacbd\uc601\uc758 \ubaa8\ud5d8", "\uc624\ub9ac\uc9c0\ub110\uc2a4", "\uc2e0\ud638\uc640 \uc18c\uc74c"], "size": 13}, {"sets": ["\uc81c\ub85c \ud22c \uc6d0"], "size": 401}, {"sets": ["\uc81c\ub85c \ud22c \uc6d0", "\uc2e0\ud638\uc640 \uc18c\uc74c"], "size": 71}, {"sets": ["\uc81c\ub85c \ud22c \uc6d0", "\uc624\ub9ac\uc9c0\ub110\uc2a4"], "size": 123}, {"sets": ["\uc81c\ub85c \ud22c \uc6d0", "\uc624\ub9ac\uc9c0\ub110\uc2a4", "\uc2e0\ud638\uc640 \uc18c\uc74c"], "size": 40}, {"sets": ["\uc81c\ub85c \ud22c \uc6d0", "\uacbd\uc601\uc758 \ubaa8\ud5d8"], "size": 82}, {"sets": ["\uc81c\ub85c \ud22c \uc6d0", "\uacbd\uc601\uc758 \ubaa8\ud5d8", "\uc2e0\ud638\uc640 \uc18c\uc74c"], "size": 29}, {"sets": ["\uc81c\ub85c \ud22c \uc6d0", "\uacbd\uc601\uc758 \ubaa8\ud5d8", "\uc624\ub9ac\uc9c0\ub110\uc2a4"], "size": 36}, {"sets": ["\uc81c\ub85c \ud22c \uc6d0", "\uacbd\uc601\uc758 \ubaa8\ud5d8", "\uc624\ub9ac\uc9c0\ub110\uc2a4", "\uc2e0\ud638\uc640 \uc18c\uc74c"], "size": 21}, {"sets": ["\uc81c\ub85c \ud22c \uc6d0", "\ud3ec\uc9c0\uc154\ub2dd POSITIONING"], "size": 67}, {"sets": ["\uc81c\ub85c \ud22c \uc6d0", "\ud3ec\uc9c0\uc154\ub2dd POSITIONING", "\uc2e0\ud638\uc640 \uc18c\uc74c"], "size": 25}, {"sets": ["\uc81c\ub85c \ud22c \uc6d0", "\ud3ec\uc9c0\uc154\ub2dd POSITIONING", "\uc624\ub9ac\uc9c0\ub110\uc2a4"], "size": 32}, {"sets": ["\uc81c\ub85c \ud22c \uc6d0", "\ud3ec\uc9c0\uc154\ub2dd POSITIONING", "\uc624\ub9ac\uc9c0\ub110\uc2a4", "\uc2e0\ud638\uc640 \uc18c\uc74c"], "size": 14}, {"sets": ["\uc81c\ub85c \ud22c \uc6d0", "\ud3ec\uc9c0\uc154\ub2dd POSITIONING", "\uacbd\uc601\uc758 \ubaa8\ud5d8"], "size": 25}, {"sets": ["\uc81c\ub85c \ud22c \uc6d0", "\ud3ec\uc9c0\uc154\ub2dd POSITIONING", "\uacbd\uc601\uc758 \ubaa8\ud5d8", "\uc2e0\ud638\uc640 \uc18c\uc74c"], "size": 14}, {"sets": ["\uc81c\ub85c \ud22c \uc6d0", "\ud3ec\uc9c0\uc154\ub2dd POSITIONING", "\uacbd\uc601\uc758 \ubaa8\ud5d8", "\uc624\ub9ac\uc9c0\ub110\uc2a4"], "size": 16}, {"sets": ["\uc81c\ub85c \ud22c \uc6d0", "\ud3ec\uc9c0\uc154\ub2dd POSITIONING", "\uacbd\uc601\uc758 \ubaa8\ud5d8", "\uc624\ub9ac\uc9c0\ub110\uc2a4", "\uc2e0\ud638\uc640 \uc18c\uc74c"], "size": 10}]}