{"titles": ["\uc624\ub798\ub41c \uc5f0\uc7a5\ud1b5", "\uc0dd\uac01\uc5d0 \uad00\ud55c \uc0dd\uac01", "\ub274\uc2a4\uc758 \uc2dc\ub300", "\uc2dc\uace8\ube75\uc9d1\uc5d0\uc11c \uc790\ubcf8\ub860\uc744 \uad7d\ub2e4", "\uc774\uc2ac\ub78c\uc758 \ub208\uc73c\ub85c \ubcf8 \uc138\uacc4\uc0ac"], "indices": [554769, 188467, 222213, 425200, 223135], "sims": [1.0, 0.5957829380118685, 0.5560392397450682, 0.5172838018121233, 0.5019060024460917], "unions": [{"sets": ["\uc774\uc2ac\ub78c\uc758 \ub208\uc73c\ub85c \ubcf8 \uc138\uacc4\uc0ac"], "size": 88}, {"sets": ["\uc2dc\uace8\ube75\uc9d1\uc5d0\uc11c \uc790\ubcf8\ub860\uc744 \uad7d\ub2e4"], "size": 287}, {"sets": ["\uc2dc\uace8\ube75\uc9d1\uc5d0\uc11c \uc790\ubcf8\ub860\uc744 \uad7d\ub2e4", "\uc774\uc2ac\ub78c\uc758 \ub208\uc73c\ub85c \ubcf8 \uc138\uacc4\uc0ac"], "size": 18}, {"sets": ["\ub274\uc2a4\uc758 \uc2dc\ub300"], "size": 395}, {"sets": ["\ub274\uc2a4\uc758 \uc2dc\ub300", "\uc774\uc2ac\ub78c\uc758 \ub208\uc73c\ub85c \ubcf8 \uc138\uacc4\uc0ac"], "size": 20}, {"sets": ["\ub274\uc2a4\uc758 \uc2dc\ub300", "\uc2dc\uace8\ube75\uc9d1\uc5d0\uc11c \uc790\ubcf8\ub860\uc744 \uad7d\ub2e4"], "size": 62}, {"sets": ["\ub274\uc2a4\uc758 \uc2dc\ub300", "\uc2dc\uace8\ube75\uc9d1\uc5d0\uc11c \uc790\ubcf8\ub860\uc744 \uad7d\ub2e4", "\uc774\uc2ac\ub78c\uc758 \ub208\uc73c\ub85c \ubcf8 \uc138\uacc4\uc0ac"], "size": 9}, {"sets": ["\uc0dd\uac01\uc5d0 \uad00\ud55c \uc0dd\uac01"], "size": 502}, {"sets": ["\uc0dd\uac01\uc5d0 \uad00\ud55c \uc0dd\uac01", "\uc774\uc2ac\ub78c\uc758 \ub208\uc73c\ub85c \ubcf8 \uc138\uacc4\uc0ac"], "size": 24}, {"sets": ["\uc0dd\uac01\uc5d0 \uad00\ud55c \uc0dd\uac01", "\uc2dc\uace8\ube75\uc9d1\uc5d0\uc11c \uc790\ubcf8\ub860\uc744 \uad7d\ub2e4"], "size": 72}, {"sets": ["\uc0dd\uac01\uc5d0 \uad00\ud55c \uc0dd\uac01", "\uc2dc\uace8\ube75\uc9d1\uc5d0\uc11c \uc790\ubcf8\ub860\uc744 \uad7d\ub2e4", "\uc774\uc2ac\ub78c\uc758 \ub208\uc73c\ub85c \ubcf8 \uc138\uacc4\uc0ac"], "size": 11}, {"sets": ["\uc0dd\uac01\uc5d0 \uad00\ud55c \uc0dd\uac01", "\ub274\uc2a4\uc758 \uc2dc\ub300"], "size": 86}, {"sets": ["\uc0dd\uac01\uc5d0 \uad00\ud55c \uc0dd\uac01", "\ub274\uc2a4\uc758 \uc2dc\ub300", "\uc774\uc2ac\ub78c\uc758 \ub208\uc73c\ub85c \ubcf8 \uc138\uacc4\uc0ac"], "size": 14}, {"sets": ["\uc0dd\uac01\uc5d0 \uad00\ud55c \uc0dd\uac01", "\ub274\uc2a4\uc758 \uc2dc\ub300", "\uc2dc\uace8\ube75\uc9d1\uc5d0\uc11c \uc790\ubcf8\ub860\uc744 \uad7d\ub2e4"], "size": 34}, {"sets": ["\uc0dd\uac01\uc5d0 \uad00\ud55c \uc0dd\uac01", "\ub274\uc2a4\uc758 \uc2dc\ub300", "\uc2dc\uace8\ube75\uc9d1\uc5d0\uc11c \uc790\ubcf8\ub860\uc744 \uad7d\ub2e4", "\uc774\uc2ac\ub78c\uc758 \ub208\uc73c\ub85c \ubcf8 \uc138\uacc4\uc0ac"], "size": 7}, {"sets": ["\uc624\ub798\ub41c \uc5f0\uc7a5\ud1b5"], "size": 106}, {"sets": ["\uc624\ub798\ub41c \uc5f0\uc7a5\ud1b5", "\uc774\uc2ac\ub78c\uc758 \ub208\uc73c\ub85c \ubcf8 \uc138\uacc4\uc0ac"], "size": 5}, {"sets": ["\uc624\ub798\ub41c \uc5f0\uc7a5\ud1b5", "\uc2dc\uace8\ube75\uc9d1\uc5d0\uc11c \uc790\ubcf8\ub860\uc744 \uad7d\ub2e4"], "size": 27}, {"sets": ["\uc624\ub798\ub41c \uc5f0\uc7a5\ud1b5", "\uc2dc\uace8\ube75\uc9d1\uc5d0\uc11c \uc790\ubcf8\ub860\uc744 \uad7d\ub2e4", "\uc774\uc2ac\ub78c\uc758 \ub208\uc73c\ub85c \ubcf8 \uc138\uacc4\uc0ac"], "size": 1}, {"sets": ["\uc624\ub798\ub41c \uc5f0\uc7a5\ud1b5", "\ub274\uc2a4\uc758 \uc2dc\ub300"], "size": 27}, {"sets": ["\uc624\ub798\ub41c \uc5f0\uc7a5\ud1b5", "\ub274\uc2a4\uc758 \uc2dc\ub300", "\uc774\uc2ac\ub78c\uc758 \ub208\uc73c\ub85c \ubcf8 \uc138\uacc4\uc0ac"], "size": 2}, {"sets": ["\uc624\ub798\ub41c \uc5f0\uc7a5\ud1b5", "\ub274\uc2a4\uc758 \uc2dc\ub300", "\uc2dc\uace8\ube75\uc9d1\uc5d0\uc11c \uc790\ubcf8\ub860\uc744 \uad7d\ub2e4"], "size": 11}, {"sets": ["\uc624\ub798\ub41c \uc5f0\uc7a5\ud1b5", "\ub274\uc2a4\uc758 \uc2dc\ub300", "\uc2dc\uace8\ube75\uc9d1\uc5d0\uc11c \uc790\ubcf8\ub860\uc744 \uad7d\ub2e4", "\uc774\uc2ac\ub78c\uc758 \ub208\uc73c\ub85c \ubcf8 \uc138\uacc4\uc0ac"], "size": 1}, {"sets": ["\uc624\ub798\ub41c \uc5f0\uc7a5\ud1b5", "\uc0dd\uac01\uc5d0 \uad00\ud55c \uc0dd\uac01"], "size": 36}, {"sets": ["\uc624\ub798\ub41c \uc5f0\uc7a5\ud1b5", "\uc0dd\uac01\uc5d0 \uad00\ud55c \uc0dd\uac01", "\uc774\uc2ac\ub78c\uc758 \ub208\uc73c\ub85c \ubcf8 \uc138\uacc4\uc0ac"], "size": 3}, {"sets": ["\uc624\ub798\ub41c \uc5f0\uc7a5\ud1b5", "\uc0dd\uac01\uc5d0 \uad00\ud55c \uc0dd\uac01", "\uc2dc\uace8\ube75\uc9d1\uc5d0\uc11c \uc790\ubcf8\ub860\uc744 \uad7d\ub2e4"], "size": 15}, {"sets": ["\uc624\ub798\ub41c \uc5f0\uc7a5\ud1b5", "\uc0dd\uac01\uc5d0 \uad00\ud55c \uc0dd\uac01", "\uc2dc\uace8\ube75\uc9d1\uc5d0\uc11c \uc790\ubcf8\ub860\uc744 \uad7d\ub2e4", "\uc774\uc2ac\ub78c\uc758 \ub208\uc73c\ub85c \ubcf8 \uc138\uacc4\uc0ac"], "size": 1}, {"sets": ["\uc624\ub798\ub41c \uc5f0\uc7a5\ud1b5", "\uc0dd\uac01\uc5d0 \uad00\ud55c \uc0dd\uac01", "\ub274\uc2a4\uc758 \uc2dc\ub300"], "size": 15}, {"sets": ["\uc624\ub798\ub41c \uc5f0\uc7a5\ud1b5", "\uc0dd\uac01\uc5d0 \uad00\ud55c \uc0dd\uac01", "\ub274\uc2a4\uc758 \uc2dc\ub300", "\uc774\uc2ac\ub78c\uc758 \ub208\uc73c\ub85c \ubcf8 \uc138\uacc4\uc0ac"], "size": 2}, {"sets": ["\uc624\ub798\ub41c \uc5f0\uc7a5\ud1b5", "\uc0dd\uac01\uc5d0 \uad00\ud55c \uc0dd\uac01", "\ub274\uc2a4\uc758 \uc2dc\ub300", "\uc2dc\uace8\ube75\uc9d1\uc5d0\uc11c \uc790\ubcf8\ub860\uc744 \uad7d\ub2e4"], "size": 6}, {"sets": ["\uc624\ub798\ub41c \uc5f0\uc7a5\ud1b5", "\uc0dd\uac01\uc5d0 \uad00\ud55c \uc0dd\uac01", "\ub274\uc2a4\uc758 \uc2dc\ub300", "\uc2dc\uace8\ube75\uc9d1\uc5d0\uc11c \uc790\ubcf8\ub860\uc744 \uad7d\ub2e4", "\uc774\uc2ac\ub78c\uc758 \ub208\uc73c\ub85c \ubcf8 \uc138\uacc4\uc0ac"], "size": 1}]}