{"titles": ["\ud30c\ubb3b\ud78c \uac70\uc778", "\ub2f9\uc2e0\uc758 \uadf8\ub9bc\uc790\ub294 \uc6d4\uc694\uc77c", "\ub514\uc5b4 \ub784\ud504 \ub85c\ub80c", "\uc6b4\ub2e4\uace0 \ub2ec\ub77c\uc9c0\ub294 \uc77c\uc740 \uc544\ubb34\uac83\ub3c4 \uc5c6\uaca0\uc9c0\ub9cc (\ub2e4\uc2dc \uc5ec\ub984, \ud55c\uc815\ud310 \ub9ac\ucee4\ubc84)", "\uc774\ub984 \uc5c6\ub294 \uc790\ub4e4\uc758 \ub3c4\uc2dc"], "indices": [554769, 188467, 222213, 425200, 223135], "sims": [1.0, 0.5407824702109095, 0.5244523096669541, 0.523193623959794, 0.5214135401673001], "unions": [{"sets": ["\uc774\ub984 \uc5c6\ub294 \uc790\ub4e4\uc758 \ub3c4\uc2dc"], "size": 52}, {"sets": ["\uc6b4\ub2e4\uace0 \ub2ec\ub77c\uc9c0\ub294 \uc77c\uc740 \uc544\ubb34\uac83\ub3c4 \uc5c6\uaca0\uc9c0\ub9cc (\ub2e4\uc2dc \uc5ec\ub984, \ud55c\uc815\ud310 \ub9ac\ucee4\ubc84)"], "size": 627}, {"sets": ["\uc6b4\ub2e4\uace0 \ub2ec\ub77c\uc9c0\ub294 \uc77c\uc740 \uc544\ubb34\uac83\ub3c4 \uc5c6\uaca0\uc9c0\ub9cc (\ub2e4\uc2dc \uc5ec\ub984, \ud55c\uc815\ud310 \ub9ac\ucee4\ubc84)", "\uc774\ub984 \uc5c6\ub294 \uc790\ub4e4\uc758 \ub3c4\uc2dc"], "size": 8}, {"sets": ["\ub514\uc5b4 \ub784\ud504 \ub85c\ub80c"], "size": 48}, {"sets": ["\ub514\uc5b4 \ub784\ud504 \ub85c\ub80c", "\uc774\ub984 \uc5c6\ub294 \uc790\ub4e4\uc758 \ub3c4\uc2dc"], "size": 2}, {"sets": ["\ub514\uc5b4 \ub784\ud504 \ub85c\ub80c", "\uc6b4\ub2e4\uace0 \ub2ec\ub77c\uc9c0\ub294 \uc77c\uc740 \uc544\ubb34\uac83\ub3c4 \uc5c6\uaca0\uc9c0\ub9cc (\ub2e4\uc2dc \uc5ec\ub984, \ud55c\uc815\ud310 \ub9ac\ucee4\ubc84)"], "size": 9}, {"sets": ["\ub514\uc5b4 \ub784\ud504 \ub85c\ub80c", "\uc6b4\ub2e4\uace0 \ub2ec\ub77c\uc9c0\ub294 \uc77c\uc740 \uc544\ubb34\uac83\ub3c4 \uc5c6\uaca0\uc9c0\ub9cc (\ub2e4\uc2dc \uc5ec\ub984, \ud55c\uc815\ud310 \ub9ac\ucee4\ubc84)", "\uc774\ub984 \uc5c6\ub294 \uc790\ub4e4\uc758 \ub3c4\uc2dc"], "size": 1}, {"sets": ["\ub2f9\uc2e0\uc758 \uadf8\ub9bc\uc790\ub294 \uc6d4\uc694\uc77c"], "size": 60}, {"sets": ["\ub2f9\uc2e0\uc758 \uadf8\ub9bc\uc790\ub294 \uc6d4\uc694\uc77c", "\uc774\ub984 \uc5c6\ub294 \uc790\ub4e4\uc758 \ub3c4\uc2dc"], "size": 3}, {"sets": ["\ub2f9\uc2e0\uc758 \uadf8\ub9bc\uc790\ub294 \uc6d4\uc694\uc77c", "\uc6b4\ub2e4\uace0 \ub2ec\ub77c\uc9c0\ub294 \uc77c\uc740 \uc544\ubb34\uac83\ub3c4 \uc5c6\uaca0\uc9c0\ub9cc (\ub2e4\uc2dc \uc5ec\ub984, \ud55c\uc815\ud310 \ub9ac\ucee4\ubc84)"], "size": 14}, {"sets": ["\ub2f9\uc2e0\uc758 \uadf8\ub9bc\uc790\ub294 \uc6d4\uc694\uc77c", "\uc6b4\ub2e4\uace0 \ub2ec\ub77c\uc9c0\ub294 \uc77c\uc740 \uc544\ubb34\uac83\ub3c4 \uc5c6\uaca0\uc9c0\ub9cc (\ub2e4\uc2dc \uc5ec\ub984, \ud55c\uc815\ud310 \ub9ac\ucee4\ubc84)", "\uc774\ub984 \uc5c6\ub294 \uc790\ub4e4\uc758 \ub3c4\uc2dc"], "size": 2}, {"sets": ["\ub2f9\uc2e0\uc758 \uadf8\ub9bc\uc790\ub294 \uc6d4\uc694\uc77c", "\ub514\uc5b4 \ub784\ud504 \ub85c\ub80c"], "size": 6}, {"sets": ["\ub2f9\uc2e0\uc758 \uadf8\ub9bc\uc790\ub294 \uc6d4\uc694\uc77c", "\ub514\uc5b4 \ub784\ud504 \ub85c\ub80c", "\uc774\ub984 \uc5c6\ub294 \uc790\ub4e4\uc758 \ub3c4\uc2dc"], "size": 1}, {"sets": ["\ub2f9\uc2e0\uc758 \uadf8\ub9bc\uc790\ub294 \uc6d4\uc694\uc77c", "\ub514\uc5b4 \ub784\ud504 \ub85c\ub80c", "\uc6b4\ub2e4\uace0 \ub2ec\ub77c\uc9c0\ub294 \uc77c\uc740 \uc544\ubb34\uac83\ub3c4 \uc5c6\uaca0\uc9c0\ub9cc (\ub2e4\uc2dc \uc5ec\ub984, \ud55c\uc815\ud310 \ub9ac\ucee4\ubc84)"], "size": 1}, {"sets": ["\ub2f9\uc2e0\uc758 \uadf8\ub9bc\uc790\ub294 \uc6d4\uc694\uc77c", "\ub514\uc5b4 \ub784\ud504 \ub85c\ub80c", "\uc6b4\ub2e4\uace0 \ub2ec\ub77c\uc9c0\ub294 \uc77c\uc740 \uc544\ubb34\uac83\ub3c4 \uc5c6\uaca0\uc9c0\ub9cc (\ub2e4\uc2dc \uc5ec\ub984, \ud55c\uc815\ud310 \ub9ac\ucee4\ubc84)", "\uc774\ub984 \uc5c6\ub294 \uc790\ub4e4\uc758 \ub3c4\uc2dc"], "size": 1}, {"sets": ["\ud30c\ubb3b\ud78c \uac70\uc778"], "size": 54}, {"sets": ["\ud30c\ubb3b\ud78c \uac70\uc778", "\uc774\ub984 \uc5c6\ub294 \uc790\ub4e4\uc758 \ub3c4\uc2dc"], "size": 4}, {"sets": ["\ud30c\ubb3b\ud78c \uac70\uc778", "\uc6b4\ub2e4\uace0 \ub2ec\ub77c\uc9c0\ub294 \uc77c\uc740 \uc544\ubb34\uac83\ub3c4 \uc5c6\uaca0\uc9c0\ub9cc (\ub2e4\uc2dc \uc5ec\ub984, \ud55c\uc815\ud310 \ub9ac\ucee4\ubc84)"], "size": 15}, {"sets": ["\ud30c\ubb3b\ud78c \uac70\uc778", "\uc6b4\ub2e4\uace0 \ub2ec\ub77c\uc9c0\ub294 \uc77c\uc740 \uc544\ubb34\uac83\ub3c4 \uc5c6\uaca0\uc9c0\ub9cc (\ub2e4\uc2dc \uc5ec\ub984, \ud55c\uc815\ud310 \ub9ac\ucee4\ubc84)", "\uc774\ub984 \uc5c6\ub294 \uc790\ub4e4\uc758 \ub3c4\uc2dc"], "size": 2}, {"sets": ["\ud30c\ubb3b\ud78c \uac70\uc778", "\ub514\uc5b4 \ub784\ud504 \ub85c\ub80c"], "size": 3}, {"sets": ["\ud30c\ubb3b\ud78c \uac70\uc778", "\ub514\uc5b4 \ub784\ud504 \ub85c\ub80c", "\uc774\ub984 \uc5c6\ub294 \uc790\ub4e4\uc758 \ub3c4\uc2dc"], "size": 1}, {"sets": ["\ud30c\ubb3b\ud78c \uac70\uc778", "\ub514\uc5b4 \ub784\ud504 \ub85c\ub80c", "\uc6b4\ub2e4\uace0 \ub2ec\ub77c\uc9c0\ub294 \uc77c\uc740 \uc544\ubb34\uac83\ub3c4 \uc5c6\uaca0\uc9c0\ub9cc (\ub2e4\uc2dc \uc5ec\ub984, \ud55c\uc815\ud310 \ub9ac\ucee4\ubc84)"], "size": 2}, {"sets": ["\ud30c\ubb3b\ud78c \uac70\uc778", "\ub514\uc5b4 \ub784\ud504 \ub85c\ub80c", "\uc6b4\ub2e4\uace0 \ub2ec\ub77c\uc9c0\ub294 \uc77c\uc740 \uc544\ubb34\uac83\ub3c4 \uc5c6\uaca0\uc9c0\ub9cc (\ub2e4\uc2dc \uc5ec\ub984, \ud55c\uc815\ud310 \ub9ac\ucee4\ubc84)", "\uc774\ub984 \uc5c6\ub294 \uc790\ub4e4\uc758 \ub3c4\uc2dc"], "size": 1}, {"sets": ["\ud30c\ubb3b\ud78c \uac70\uc778", "\ub2f9\uc2e0\uc758 \uadf8\ub9bc\uc790\ub294 \uc6d4\uc694\uc77c"], "size": 4}, {"sets": ["\ud30c\ubb3b\ud78c \uac70\uc778", "\ub2f9\uc2e0\uc758 \uadf8\ub9bc\uc790\ub294 \uc6d4\uc694\uc77c", "\uc774\ub984 \uc5c6\ub294 \uc790\ub4e4\uc758 \ub3c4\uc2dc"], "size": 1}, {"sets": ["\ud30c\ubb3b\ud78c \uac70\uc778", "\ub2f9\uc2e0\uc758 \uadf8\ub9bc\uc790\ub294 \uc6d4\uc694\uc77c", "\uc6b4\ub2e4\uace0 \ub2ec\ub77c\uc9c0\ub294 \uc77c\uc740 \uc544\ubb34\uac83\ub3c4 \uc5c6\uaca0\uc9c0\ub9cc (\ub2e4\uc2dc \uc5ec\ub984, \ud55c\uc815\ud310 \ub9ac\ucee4\ubc84)"], "size": 2}, {"sets": ["\ud30c\ubb3b\ud78c \uac70\uc778", "\ub2f9\uc2e0\uc758 \uadf8\ub9bc\uc790\ub294 \uc6d4\uc694\uc77c", "\uc6b4\ub2e4\uace0 \ub2ec\ub77c\uc9c0\ub294 \uc77c\uc740 \uc544\ubb34\uac83\ub3c4 \uc5c6\uaca0\uc9c0\ub9cc (\ub2e4\uc2dc \uc5ec\ub984, \ud55c\uc815\ud310 \ub9ac\ucee4\ubc84)", "\uc774\ub984 \uc5c6\ub294 \uc790\ub4e4\uc758 \ub3c4\uc2dc"], "size": 1}, {"sets": ["\ud30c\ubb3b\ud78c \uac70\uc778", "\ub2f9\uc2e0\uc758 \uadf8\ub9bc\uc790\ub294 \uc6d4\uc694\uc77c", "\ub514\uc5b4 \ub784\ud504 \ub85c\ub80c"], "size": 2}, {"sets": ["\ud30c\ubb3b\ud78c \uac70\uc778", "\ub2f9\uc2e0\uc758 \uadf8\ub9bc\uc790\ub294 \uc6d4\uc694\uc77c", "\ub514\uc5b4 \ub784\ud504 \ub85c\ub80c", "\uc774\ub984 \uc5c6\ub294 \uc790\ub4e4\uc758 \ub3c4\uc2dc"], "size": 1}, {"sets": ["\ud30c\ubb3b\ud78c \uac70\uc778", "\ub2f9\uc2e0\uc758 \uadf8\ub9bc\uc790\ub294 \uc6d4\uc694\uc77c", "\ub514\uc5b4 \ub784\ud504 \ub85c\ub80c", "\uc6b4\ub2e4\uace0 \ub2ec\ub77c\uc9c0\ub294 \uc77c\uc740 \uc544\ubb34\uac83\ub3c4 \uc5c6\uaca0\uc9c0\ub9cc (\ub2e4\uc2dc \uc5ec\ub984, \ud55c\uc815\ud310 \ub9ac\ucee4\ubc84)"], "size": 1}, {"sets": ["\ud30c\ubb3b\ud78c \uac70\uc778", "\ub2f9\uc2e0\uc758 \uadf8\ub9bc\uc790\ub294 \uc6d4\uc694\uc77c", "\ub514\uc5b4 \ub784\ud504 \ub85c\ub80c", "\uc6b4\ub2e4\uace0 \ub2ec\ub77c\uc9c0\ub294 \uc77c\uc740 \uc544\ubb34\uac83\ub3c4 \uc5c6\uaca0\uc9c0\ub9cc (\ub2e4\uc2dc \uc5ec\ub984, \ud55c\uc815\ud310 \ub9ac\ucee4\ubc84)", "\uc774\ub984 \uc5c6\ub294 \uc790\ub4e4\uc758 \ub3c4\uc2dc"], "size": 1}]}