{"titles": ["\uc720\ub7fd\uc758 \ucc45\ub9c8\uc744\uc744 \uac00\ub2e4", "\uba85\uc2ec\ubcf4\uac10", "\ub17c\uc5b4", "\uc548\uc528\uac00\ud6c8", "\ubc95\uad6c\uacbd"], "indices": [554769, 188467, 222213, 425200, 223135], "sims": [0.9999999999999997, 0.5685690425380785, 0.5226354854540259, 0.5219574750426111, 0.5149827889617256], "unions": [{"sets": ["\ubc95\uad6c\uacbd"], "size": 110}, {"sets": ["\uc548\uc528\uac00\ud6c8"], "size": 86}, {"sets": ["\uc548\uc528\uac00\ud6c8", "\ubc95\uad6c\uacbd"], "size": 56}, {"sets": ["\ub17c\uc5b4"], "size": 590}, {"sets": ["\ub17c\uc5b4", "\ubc95\uad6c\uacbd"], "size": 85}, {"sets": ["\ub17c\uc5b4", "\uc548\uc528\uac00\ud6c8"], "size": 66}, {"sets": ["\ub17c\uc5b4", "\uc548\uc528\uac00\ud6c8", "\ubc95\uad6c\uacbd"], "size": 48}, {"sets": ["\uba85\uc2ec\ubcf4\uac10"], "size": 164}, {"sets": ["\uba85\uc2ec\ubcf4\uac10", "\ubc95\uad6c\uacbd"], "size": 59}, {"sets": ["\uba85\uc2ec\ubcf4\uac10", "\uc548\uc528\uac00\ud6c8"], "size": 67}, {"sets": ["\uba85\uc2ec\ubcf4\uac10", "\uc548\uc528\uac00\ud6c8", "\ubc95\uad6c\uacbd"], "size": 51}, {"sets": ["\uba85\uc2ec\ubcf4\uac10", "\ub17c\uc5b4"], "size": 100}, {"sets": ["\uba85\uc2ec\ubcf4\uac10", "\ub17c\uc5b4", "\ubc95\uad6c\uacbd"], "size": 51}, {"sets": ["\uba85\uc2ec\ubcf4\uac10", "\ub17c\uc5b4", "\uc548\uc528\uac00\ud6c8"], "size": 57}, {"sets": ["\uba85\uc2ec\ubcf4\uac10", "\ub17c\uc5b4", "\uc548\uc528\uac00\ud6c8", "\ubc95\uad6c\uacbd"], "size": 44}, {"sets": ["\uc720\ub7fd\uc758 \ucc45\ub9c8\uc744\uc744 \uac00\ub2e4"], "size": 63}, {"sets": ["\uc720\ub7fd\uc758 \ucc45\ub9c8\uc744\uc744 \uac00\ub2e4", "\ubc95\uad6c\uacbd"], "size": 8}, {"sets": ["\uc720\ub7fd\uc758 \ucc45\ub9c8\uc744\uc744 \uac00\ub2e4", "\uc548\uc528\uac00\ud6c8"], "size": 7}, {"sets": ["\uc720\ub7fd\uc758 \ucc45\ub9c8\uc744\uc744 \uac00\ub2e4", "\uc548\uc528\uac00\ud6c8", "\ubc95\uad6c\uacbd"], "size": 7}, {"sets": ["\uc720\ub7fd\uc758 \ucc45\ub9c8\uc744\uc744 \uac00\ub2e4", "\ub17c\uc5b4"], "size": 17}, {"sets": ["\uc720\ub7fd\uc758 \ucc45\ub9c8\uc744\uc744 \uac00\ub2e4", "\ub17c\uc5b4", "\ubc95\uad6c\uacbd"], "size": 7}, {"sets": ["\uc720\ub7fd\uc758 \ucc45\ub9c8\uc744\uc744 \uac00\ub2e4", "\ub17c\uc5b4", "\uc548\uc528\uac00\ud6c8"], "size": 6}, {"sets": ["\uc720\ub7fd\uc758 \ucc45\ub9c8\uc744\uc744 \uac00\ub2e4", "\ub17c\uc5b4", "\uc548\uc528\uac00\ud6c8", "\ubc95\uad6c\uacbd"], "size": 6}, {"sets": ["\uc720\ub7fd\uc758 \ucc45\ub9c8\uc744\uc744 \uac00\ub2e4", "\uba85\uc2ec\ubcf4\uac10"], "size": 10}, {"sets": ["\uc720\ub7fd\uc758 \ucc45\ub9c8\uc744\uc744 \uac00\ub2e4", "\uba85\uc2ec\ubcf4\uac10", "\ubc95\uad6c\uacbd"], "size": 6}, {"sets": ["\uc720\ub7fd\uc758 \ucc45\ub9c8\uc744\uc744 \uac00\ub2e4", "\uba85\uc2ec\ubcf4\uac10", "\uc548\uc528\uac00\ud6c8"], "size": 6}, {"sets": ["\uc720\ub7fd\uc758 \ucc45\ub9c8\uc744\uc744 \uac00\ub2e4", "\uba85\uc2ec\ubcf4\uac10", "\uc548\uc528\uac00\ud6c8", "\ubc95\uad6c\uacbd"], "size": 6}, {"sets": ["\uc720\ub7fd\uc758 \ucc45\ub9c8\uc744\uc744 \uac00\ub2e4", "\uba85\uc2ec\ubcf4\uac10", "\ub17c\uc5b4"], "size": 9}, {"sets": ["\uc720\ub7fd\uc758 \ucc45\ub9c8\uc744\uc744 \uac00\ub2e4", "\uba85\uc2ec\ubcf4\uac10", "\ub17c\uc5b4", "\ubc95\uad6c\uacbd"], "size": 5}, {"sets": ["\uc720\ub7fd\uc758 \ucc45\ub9c8\uc744\uc744 \uac00\ub2e4", "\uba85\uc2ec\ubcf4\uac10", "\ub17c\uc5b4", "\uc548\uc528\uac00\ud6c8"], "size": 5}, {"sets": ["\uc720\ub7fd\uc758 \ucc45\ub9c8\uc744\uc744 \uac00\ub2e4", "\uba85\uc2ec\ubcf4\uac10", "\ub17c\uc5b4", "\uc548\uc528\uac00\ud6c8", "\ubc95\uad6c\uacbd"], "size": 5}]}