{"titles": ["\ub098\ub294 \uac00\ud574\uc790\uc758 \uc5c4\ub9c8\uc785\ub2c8\ub2e4", "\ubb34\uae30\uc5ec \uc798 \uc788\uc5b4\ub77c", "\ub300\uc131\ub2f9", "\ud544\ub984 \uc18d\uc744 \uac77\ub2e4", "\ube4c\ud5ec\ub984 \ub9c8\uc774\uc2a4\ud130\uc758 \uc218\uc5c5\uc2dc\ub300 2"], "indices": [554769, 188467, 222213, 425200, 223135], "sims": [1.0, 0.5756591208305267, 0.561049295563582, 0.5534849264498308, 0.5524685096172492], "unions": [{"sets": ["\ube4c\ud5ec\ub984 \ub9c8\uc774\uc2a4\ud130\uc758 \uc218\uc5c5\uc2dc\ub300 2"], "size": 51}, {"sets": ["\ud544\ub984 \uc18d\uc744 \uac77\ub2e4"], "size": 92}, {"sets": ["\ud544\ub984 \uc18d\uc744 \uac77\ub2e4", "\ube4c\ud5ec\ub984 \ub9c8\uc774\uc2a4\ud130\uc758 \uc218\uc5c5\uc2dc\ub300 2"], "size": 3}, {"sets": ["\ub300\uc131\ub2f9"], "size": 231}, {"sets": ["\ub300\uc131\ub2f9", "\ube4c\ud5ec\ub984 \ub9c8\uc774\uc2a4\ud130\uc758 \uc218\uc5c5\uc2dc\ub300 2"], "size": 7}, {"sets": ["\ub300\uc131\ub2f9", "\ud544\ub984 \uc18d\uc744 \uac77\ub2e4"], "size": 18}, {"sets": ["\ub300\uc131\ub2f9", "\ud544\ub984 \uc18d\uc744 \uac77\ub2e4", "\ube4c\ud5ec\ub984 \ub9c8\uc774\uc2a4\ud130\uc758 \uc218\uc5c5\uc2dc\ub300 2"], "size": 2}, {"sets": ["\ubb34\uae30\uc5ec \uc798 \uc788\uc5b4\ub77c"], "size": 59}, {"sets": ["\ubb34\uae30\uc5ec \uc798 \uc788\uc5b4\ub77c", "\ube4c\ud5ec\ub984 \ub9c8\uc774\uc2a4\ud130\uc758 \uc218\uc5c5\uc2dc\ub300 2"], "size": 11}, {"sets": ["\ubb34\uae30\uc5ec \uc798 \uc788\uc5b4\ub77c", "\ud544\ub984 \uc18d\uc744 \uac77\ub2e4"], "size": 5}, {"sets": ["\ubb34\uae30\uc5ec \uc798 \uc788\uc5b4\ub77c", "\ud544\ub984 \uc18d\uc744 \uac77\ub2e4", "\ube4c\ud5ec\ub984 \ub9c8\uc774\uc2a4\ud130\uc758 \uc218\uc5c5\uc2dc\ub300 2"], "size": 2}, {"sets": ["\ubb34\uae30\uc5ec \uc798 \uc788\uc5b4\ub77c", "\ub300\uc131\ub2f9"], "size": 10}, {"sets": ["\ubb34\uae30\uc5ec \uc798 \uc788\uc5b4\ub77c", "\ub300\uc131\ub2f9", "\ube4c\ud5ec\ub984 \ub9c8\uc774\uc2a4\ud130\uc758 \uc218\uc5c5\uc2dc\ub300 2"], "size": 1}, {"sets": ["\ubb34\uae30\uc5ec \uc798 \uc788\uc5b4\ub77c", "\ub300\uc131\ub2f9", "\ud544\ub984 \uc18d\uc744 \uac77\ub2e4"], "size": 2}, {"sets": ["\ubb34\uae30\uc5ec \uc798 \uc788\uc5b4\ub77c", "\ub300\uc131\ub2f9", "\ud544\ub984 \uc18d\uc744 \uac77\ub2e4", "\ube4c\ud5ec\ub984 \ub9c8\uc774\uc2a4\ud130\uc758 \uc218\uc5c5\uc2dc\ub300 2"], "size": 1}, {"sets": ["\ub098\ub294 \uac00\ud574\uc790\uc758 \uc5c4\ub9c8\uc785\ub2c8\ub2e4"], "size": 221}, {"sets": ["\ub098\ub294 \uac00\ud574\uc790\uc758 \uc5c4\ub9c8\uc785\ub2c8\ub2e4", "\ube4c\ud5ec\ub984 \ub9c8\uc774\uc2a4\ud130\uc758 \uc218\uc5c5\uc2dc\ub300 2"], "size": 4}, {"sets": ["\ub098\ub294 \uac00\ud574\uc790\uc758 \uc5c4\ub9c8\uc785\ub2c8\ub2e4", "\ud544\ub984 \uc18d\uc744 \uac77\ub2e4"], "size": 18}, {"sets": ["\ub098\ub294 \uac00\ud574\uc790\uc758 \uc5c4\ub9c8\uc785\ub2c8\ub2e4", "\ud544\ub984 \uc18d\uc744 \uac77\ub2e4", "\ube4c\ud5ec\ub984 \ub9c8\uc774\uc2a4\ud130\uc758 \uc218\uc5c5\uc2dc\ub300 2"], "size": 2}, {"sets": ["\ub098\ub294 \uac00\ud574\uc790\uc758 \uc5c4\ub9c8\uc785\ub2c8\ub2e4", "\ub300\uc131\ub2f9"], "size": 34}, {"sets": ["\ub098\ub294 \uac00\ud574\uc790\uc758 \uc5c4\ub9c8\uc785\ub2c8\ub2e4", "\ub300\uc131\ub2f9", "\ube4c\ud5ec\ub984 \ub9c8\uc774\uc2a4\ud130\uc758 \uc218\uc5c5\uc2dc\ub300 2"], "size": 1}, {"sets": ["\ub098\ub294 \uac00\ud574\uc790\uc758 \uc5c4\ub9c8\uc785\ub2c8\ub2e4", "\ub300\uc131\ub2f9", "\ud544\ub984 \uc18d\uc744 \uac77\ub2e4"], "size": 9}, {"sets": ["\ub098\ub294 \uac00\ud574\uc790\uc758 \uc5c4\ub9c8\uc785\ub2c8\ub2e4", "\ub300\uc131\ub2f9", "\ud544\ub984 \uc18d\uc744 \uac77\ub2e4", "\ube4c\ud5ec\ub984 \ub9c8\uc774\uc2a4\ud130\uc758 \uc218\uc5c5\uc2dc\ub300 2"], "size": 1}, {"sets": ["\ub098\ub294 \uac00\ud574\uc790\uc758 \uc5c4\ub9c8\uc785\ub2c8\ub2e4", "\ubb34\uae30\uc5ec \uc798 \uc788\uc5b4\ub77c"], "size": 9}, {"sets": ["\ub098\ub294 \uac00\ud574\uc790\uc758 \uc5c4\ub9c8\uc785\ub2c8\ub2e4", "\ubb34\uae30\uc5ec \uc798 \uc788\uc5b4\ub77c", "\ube4c\ud5ec\ub984 \ub9c8\uc774\uc2a4\ud130\uc758 \uc218\uc5c5\uc2dc\ub300 2"], "size": 3}, {"sets": ["\ub098\ub294 \uac00\ud574\uc790\uc758 \uc5c4\ub9c8\uc785\ub2c8\ub2e4", "\ubb34\uae30\uc5ec \uc798 \uc788\uc5b4\ub77c", "\ud544\ub984 \uc18d\uc744 \uac77\ub2e4"], "size": 4}, {"sets": ["\ub098\ub294 \uac00\ud574\uc790\uc758 \uc5c4\ub9c8\uc785\ub2c8\ub2e4", "\ubb34\uae30\uc5ec \uc798 \uc788\uc5b4\ub77c", "\ud544\ub984 \uc18d\uc744 \uac77\ub2e4", "\ube4c\ud5ec\ub984 \ub9c8\uc774\uc2a4\ud130\uc758 \uc218\uc5c5\uc2dc\ub300 2"], "size": 2}, {"sets": ["\ub098\ub294 \uac00\ud574\uc790\uc758 \uc5c4\ub9c8\uc785\ub2c8\ub2e4", "\ubb34\uae30\uc5ec \uc798 \uc788\uc5b4\ub77c", "\ub300\uc131\ub2f9"], "size": 4}, {"sets": ["\ub098\ub294 \uac00\ud574\uc790\uc758 \uc5c4\ub9c8\uc785\ub2c8\ub2e4", "\ubb34\uae30\uc5ec \uc798 \uc788\uc5b4\ub77c", "\ub300\uc131\ub2f9", "\ube4c\ud5ec\ub984 \ub9c8\uc774\uc2a4\ud130\uc758 \uc218\uc5c5\uc2dc\ub300 2"], "size": 1}, {"sets": ["\ub098\ub294 \uac00\ud574\uc790\uc758 \uc5c4\ub9c8\uc785\ub2c8\ub2e4", "\ubb34\uae30\uc5ec \uc798 \uc788\uc5b4\ub77c", "\ub300\uc131\ub2f9", "\ud544\ub984 \uc18d\uc744 \uac77\ub2e4"], "size": 2}, {"sets": ["\ub098\ub294 \uac00\ud574\uc790\uc758 \uc5c4\ub9c8\uc785\ub2c8\ub2e4", "\ubb34\uae30\uc5ec \uc798 \uc788\uc5b4\ub77c", "\ub300\uc131\ub2f9", "\ud544\ub984 \uc18d\uc744 \uac77\ub2e4", "\ube4c\ud5ec\ub984 \ub9c8\uc774\uc2a4\ud130\uc758 \uc218\uc5c5\uc2dc\ub300 2"], "size": 1}]}